README
setup.py
esprima/__init__.py
esprima/__main__.py
esprima/character.py
esprima/comment_handler.orig.py
esprima/comment_handler.py
esprima/compat.py
esprima/error_handler.py
esprima/esprima.py
esprima/jsx_nodes.py
esprima/jsx_parser.py
esprima/jsx_syntax.py
esprima/messages.py
esprima/nodes.py
esprima/objects.py
esprima/parser.py
esprima/scanner.py
esprima/syntax.py
esprima/token.py
esprima/tokenizer.py
esprima/utils.py
esprima/visitor.py
esprima/xhtml_entities.py
esprima.egg-info/PKG-INFO
esprima.egg-info/SOURCES.txt
esprima.egg-info/dependency_links.txt
esprima.egg-info/entry_points.txt
esprima.egg-info/pbr.json
esprima.egg-info/top_level.txt